setup.py
pypraticot5/__init__.py
pypraticot5/github.py
pypraticot5.egg-info/PKG-INFO
pypraticot5.egg-info/SOURCES.txt
pypraticot5.egg-info/dependency_links.txt
pypraticot5.egg-info/not-zip-safe
pypraticot5.egg-info/requires.txt
pypraticot5.egg-info/top_level.txt